{"trial_id": "00", "hyperparameters": {"space": [{"class_name": "Int", "config": {"name": "filters", "default": null, "conditions": [], "min_value": 32, "max_value": 256, "step": 32, "sampling": "linear"}}, {"class_name": "Int", "config": {"name": "kernel_size", "default": null, "conditions": [], "min_value": 2, "max_value": 12, "step": 2, "sampling": "linear"}}, {"class_name": "Choice", "config": {"name": "activation", "default": "relu", "conditions": [], "values": ["relu", "sigmoid"], "ordered": false}}], "values": {"filters": 160, "kernel_size": 6, "activation": "relu"}}, "metrics": {"metrics": {}}, "score": null, "best_step": 0, "status": "RUNNING", "message": null}